pyebas/__init__.py
pyebas/main.py
pyebas/version.py
pyebas/ebas_db/__init__.py
pyebas/ebas_db/db.py
pyebas/ebas_db/files_io.py
pyebas/ebas_db/query.py
pyebas/ebas_db/site_index.py
pyebas/ebas_db/value_index.py
pyebas/ebas_downloader/__init__.py
pyebas/ebas_downloader/csv_exporter.py
pyebas/ebas_downloader/downloader.py
pyebas/utilities/__init__.py
pyebas/utilities/utilities.py
pyebas-0.1.6.dist-info/LICENSE
pyebas-0.1.6.dist-info/METADATA
pyebas-0.1.6.dist-info/WHEEL
pyebas-0.1.6.dist-info/entry_points.txt
pyebas-0.1.6.dist-info/top_level.txt
pyebas-0.1.6.dist-info/RECORD
