Metadata-Version: 2.1
Name: pyebas
Version: 0.1.6
Summary: Easy download and export EBAS data
Home-page: https://github.com/defve1988/pyebas
Author: Chuanlong Zhou
Author-email: <zhouchuanlong1988@gmail.com>
License: UNKNOWN
Keywords: python,ebas,air pollution,ftp
Platform: UNKNOWN
Classifier: Development Status :: 4 - Beta
Classifier: Intended Audience :: Science/Research
Classifier: Programming Language :: Python :: 3
Classifier: Operating System :: Unix
Classifier: Operating System :: MacOS :: MacOS X
Classifier: Operating System :: Microsoft :: Windows
Requires-Dist: numpy
Requires-Dist: pandas
Requires-Dist: xarray
Requires-Dist: pycountry
Requires-Dist: bs4
Requires-Dist: wget
Requires-Dist: tqdm
